antorum/__init__.py
antorum/actions.py
antorum/cache.py
antorum/damage.py
antorum/game.py
antorum/multiplayer.py
antorum/player.py
antorum/utils.py
antorum/packets/__init__.py
antorum/packets/barter_close.py
antorum/packets/barter_move.py
antorum/packets/barter_open.py
antorum/packets/character_creation.py
antorum/packets/chat.py
antorum/packets/combat_start.py
antorum/packets/combat_stop.py
antorum/packets/entity_despawn.py
antorum/packets/entity_spawn.py
antorum/packets/entity_state.py
antorum/packets/exp.py
antorum/packets/halt.py
antorum/packets/handshake.py
antorum/packets/interact.py
antorum/packets/inventory.py
antorum/packets/inventory_add.py
antorum/packets/inventory_item_drop.py
antorum/packets/inventory_read_item.py
antorum/packets/inventory_remove.py
antorum/packets/item.py
antorum/packets/load_complete.py
antorum/packets/login.py
antorum/packets/move.py
antorum/packets/move_failed.py
antorum/packets/packet.py
antorum/packets/skills.py
antorum/packets/stats.py
antorum/packets/world_entities.py
Antorum-0.0.1.dist-info/LICENSE.txt
Antorum-0.0.1.dist-info/METADATA
Antorum-0.0.1.dist-info/WHEEL
Antorum-0.0.1.dist-info/top_level.txt
Antorum-0.0.1.dist-info/RECORD
