Metadata-Version: 2.1
Name: Antorum
Version: 0.0.1
Summary: A Python package to write bots for the game Antorum!
Home-page: https://github.com/Svenskithesource/AntorumBot
Author: svenskithesource
Author-email: 40274381+Svenskithesource@users.noreply.github.com
License: MIT
Platform: any
Classifier: Development Status :: 4 - Beta
Classifier: Programming Language :: Python
Requires-Python: >=3.3
License-File: LICENSE.txt
Requires-Dist: pycryptodomex
Requires-Dist: importlib-metadata ; python_version < "3.8"
Provides-Extra: testing
